iota_balance_change_alert/__init__.py
iota_balance_change_alert/alerts.py
iota_balance_change_alert/cli.py
iota_balance_change_alert/iota_balance_change_alert.py
iota_balance_change_alert-0.1.2.data/data/config/config.ini.example
iota_balance_change_alert-0.1.2.dist-info/DESCRIPTION.rst
iota_balance_change_alert-0.1.2.dist-info/METADATA
iota_balance_change_alert-0.1.2.dist-info/RECORD
iota_balance_change_alert-0.1.2.dist-info/WHEEL
iota_balance_change_alert-0.1.2.dist-info/entry_points.txt
iota_balance_change_alert-0.1.2.dist-info/metadata.json
iota_balance_change_alert-0.1.2.dist-info/top_level.txt
