Metadata-Version: 2.0
Name: iota-balance-change-alert
Version: 0.1.2
Summary: IOTA Balance Change Alert checks the balance on one or more addresses at a specified interval and alerts the user if there's any change in balance.
Home-page: https://github.com/plenarius/iota_balance_change_alert
Author: James Greenhalgh
Author-email: plenarius@gmail.com
License: MIT license
Keywords: iota_balance_change_alert
Platform: UNKNOWN
Classifier: Development Status :: 2 - Pre-Alpha
Classifier: Intended Audience :: Developers
Classifier: License :: OSI Approved :: MIT License
Classifier: Natural Language :: English
Classifier: Programming Language :: Python :: 2
Classifier: Programming Language :: Python :: 2.7
Classifier: Programming Language :: Python :: 3
Classifier: Programming Language :: Python :: 3.5
Classifier: Programming Language :: Python :: 3.6
Requires-Dist: Click (>=6.0)
Requires-Dist: pyota (>=2.0)
Requires-Dist: schedule (>=0.5.0)
Requires-Dist: ConfigParser; python_version < "3"
Requires-Dist: configparser; python_version >= "3"
Provides-Extra: Twilio
Requires-Dist: twilio (>0.6); extra == 'Twilio'
